citrine/__init__.py
citrine/__init__.pyi
citrine/brightness_heralding.py
citrine/brightness_heralding.pyi
citrine/citrine.py
citrine/citrine.pyi
citrine/crystals.py
citrine/crystals.pyi
citrine/phase_matching.py
citrine/phase_matching.pyi
citrine/pump_envelope.py
citrine/pump_envelope.pyi
citrine/py.typed
citrinespdc-0.2.0.dist-info/licenses/LICENSE
citrinespdc-0.2.0.dist-info/METADATA
citrinespdc-0.2.0.dist-info/WHEEL
citrinespdc-0.2.0.dist-info/top_level.txt
citrinespdc-0.2.0.dist-info/RECORD
