Metadata-Version: 2.4
Name: citrineSPDC
Version: 0.2.0
Author-email: Peter Thomas Barrow <peter.barrow.93@gmail.com>
License:                     GNU AFFERO GENERAL PUBLIC LICENSE
Project-URL: Homepage, https://github.com/Peter-Barrow/citrine
Project-URL: Repository, https://github.com/Peter-Barrow/citrine.git
Project-URL: Issues, https://github.com/Peter-Barrow/citrine/issues
License-File: LICENSE
Requires-Dist: numpy
Requires-Dist: scipy
Requires-Dist: matplotlib
Requires-Dist: seaborn
Requires-Dist: tqdm
Requires-Dist: numba>=0.60.0
Requires-Dist: mkdocs>=1.6.1
Requires-Dist: mkdocs-material>=9.6.9
Requires-Dist: mkdocstrings[python]>=0.29.0
Requires-Dist: mkdocs-jupyter>=0.25.1
Dynamic: license-file
